ouigo/__init__.py
ouigo/ouigo.py
ouigo/seasson.py
ouigo/stations.py
ouigo/types_class.py
ouigo/utils.py
ouigo-1.0.4.dist-info/LICENSE.md
ouigo-1.0.4.dist-info/METADATA
ouigo-1.0.4.dist-info/WHEEL
ouigo-1.0.4.dist-info/top_level.txt
ouigo-1.0.4.dist-info/RECORD
