Metadata-Version: 2.1
Name: ouigo
Version: 1.0.4
Summary: A module which allows you to retrieve data about the cheapest one-way travels of Ouigo in a date range.
Home-page: https://github.com/RicardoAlegreMiranda/ouigo
Author: Ricardo Alegre
Author-email: ricardomanuel.alegre@gmail.com
Classifier: Programming Language :: Python :: 3
Classifier: Operating System :: OS Independent
License-File: LICENSE.md
Requires-Dist: requests
